irdf/__init__.py
irdf/graph.py
irdf/table.py
irdf-1.4.dist-info/LICENSE
irdf-1.4.dist-info/METADATA
irdf-1.4.dist-info/WHEEL
irdf-1.4.dist-info/top_level.txt
irdf-1.4.dist-info/RECORD
