Metadata-Version: 2.1
Name: irdf
Version: 1.4
Summary: Jupyter extension for interacting with RDF graphs
Author-email: Benno Kruit <b.b.kruit@vu.nl>
Project-URL: Homepage, https://github.com/bennokr/irdf
Project-URL: Issues, https://github.com/bennokr/irdf/issues
Keywords: ipython,jupyter,visualization,interaction,interact
Classifier: Programming Language :: Python :: 3
Classifier: License :: OSI Approved :: MIT License
Classifier: Operating System :: OS Independent
Requires-Python: >=3.8
License-File: LICENSE
Requires-Dist: rdflib
Requires-Dist: requests
Requires-Dist: pandas
Requires-Dist: itables
Requires-Dist: ipycytoscape
